pybeecn2/__init__.py
pybeecn2/cli.py
pybeecn2/vis/__init__.py
pybeecn2/vis/cli.py
pybeecn2/vis/mapping.py
pybeecn2/vis/run.py
tests/__init__.py
tests/pybeecn2/__init__.py
tests/pybeecn2/test_install.py
tests/pybeecn2/vis/__init__.py
tests/pybeecn2/vis/test_run.py
pybeecn2-0.0.7.dist-info/LICENSE
pybeecn2-0.0.7.dist-info/METADATA
pybeecn2-0.0.7.dist-info/WHEEL
pybeecn2-0.0.7.dist-info/entry_points.txt
pybeecn2-0.0.7.dist-info/top_level.txt
pybeecn2-0.0.7.dist-info/RECORD
