Metadata-Version: 2.1
Name: pybeecn2
Version: 0.0.7
Summary: Ability to view Portland Demographic Data
Home-page: https://github.com/glmcbr06/pybeecn2
Author: Gabriel McBride
Author-email: gabe.l.mcbride@gmail.com
License: UNKNOWN
Platform: UNKNOWN
Classifier: Programming Language :: Python :: 3
Classifier: License :: OSI Approved :: MIT License
Classifier: Operating System :: OS Independent
Requires-Python: >=3.6
Requires-Dist: numpy
Requires-Dist: matplotlib
Requires-Dist: folium
Requires-Dist: geopandas
